setup.cfg
setup.py
replicaCortex/Shortcuts.py
replicaCortex/__init__.py
replicaCortex.egg-info/PKG-INFO
replicaCortex.egg-info/SOURCES.txt
replicaCortex.egg-info/dependency_links.txt
replicaCortex.egg-info/not-zip-safe
replicaCortex.egg-info/top_level.txt