Metadata-Version: 2.1
Name: replicaCortex
Version: 0.0.4
Summary: Taa
Author-email: serezha.belikov.05@mail.ru
